ipython_args/__init__.py
ipython_args/utils.py
IPYTHON_ARGPARSE-1.0.1.dist-info/METADATA
IPYTHON_ARGPARSE-1.0.1.dist-info/WHEEL
IPYTHON_ARGPARSE-1.0.1.dist-info/top_level.txt
IPYTHON_ARGPARSE-1.0.1.dist-info/RECORD
