Metadata-Version: 2.1
Name: IPYTHON-ARGPARSE
Version: 1.0.1
Summary: A utility for seamless argument parsing in IPython notebooks and Python scripts.
Home-page: https://github.com/qkaTlehdrnf/IpythonArguments
Author: Kim, Won-Joong
Author-email: wonjoong11@yonsei.ac.kr
Classifier: Development Status :: 4 - Beta
Classifier: Intended Audience :: Developers
Classifier: License :: OSI Approved :: MIT License
Classifier: Programming Language :: Python :: 3
Classifier: Programming Language :: Python :: 3.4
Classifier: Programming Language :: Python :: 3.5
Classifier: Programming Language :: Python :: 3.6
Classifier: Programming Language :: Python :: 3.7
Classifier: Programming Language :: Python :: 3.8
Classifier: Programming Language :: Python :: 3.9
Classifier: Programming Language :: Python :: 3.10
Classifier: Framework :: IPython
Classifier: Topic :: Software Development :: Libraries :: Python Modules
Requires-Python: >=3.4
Requires-Dist: easydict
Requires-Dist: ipython
